custom_qr/__init__.py
custom_qr/charset.py
custom_qr/constraints.py
custom_qr/custom_qr.py
custom_qr/dataConverter.py
custom_qr/errorCorrection.py
custom_qr/generate_qr.py
custom_qr/qrCode.py
custom_qr-0.9.5.dist-info/LICENSE
custom_qr-0.9.5.dist-info/METADATA
custom_qr-0.9.5.dist-info/WHEEL
custom_qr-0.9.5.dist-info/top_level.txt
custom_qr-0.9.5.dist-info/RECORD
