Metadata-Version: 2.1
Name: custom-qr
Version: 0.9.5
Summary: Generate and customize QR codes
Home-page: https://github.com/DaYe03/custom_qr.git
Author: Daniele Ye
Author-email: daniele.ye03@gmail.com
Classifier: Programming Language :: Python :: 3
Classifier: License :: OSI Approved :: MIT License
Classifier: Operating System :: OS Independent
Requires-Python: >=3.6
License-File: LICENSE
Requires-Dist: numpy
Requires-Dist: opencv-python
